README.md
setup.py
src/vdk/plugin/control_api_auth/auth_config.py
src/vdk/plugin/control_api_auth/auth_exception.py
src/vdk/plugin/control_api_auth/auth_request_values.py
src/vdk/plugin/control_api_auth/authentication.py
src/vdk/plugin/control_api_auth/autorization_code_auth.py
src/vdk/plugin/control_api_auth/base_auth.py
src/vdk/plugin/control_api_auth/login_types.py
src/vdk_control_api_auth.egg-info/PKG-INFO
src/vdk_control_api_auth.egg-info/SOURCES.txt
src/vdk_control_api_auth.egg-info/dependency_links.txt
src/vdk_control_api_auth.egg-info/requires.txt
src/vdk_control_api_auth.egg-info/top_level.txt
tests/test_api_token_auth.py
tests/test_authorization_code_auth.py
tests/test_core_auth.py